layered_window.pyd
layered_window-stubs/__init__.pyi
layered_window-0.9.4.dist-info/LICENSE
layered_window-0.9.4.dist-info/METADATA
layered_window-0.9.4.dist-info/WHEEL
layered_window-0.9.4.dist-info/top_level.txt
layered_window-0.9.4.dist-info/RECORD
